pyLDT_cosmo/__init__.py
pyLDT_cosmo/compute_pk.py
pyLDT_cosmo/growth_eqns.py
pyLDT_cosmo/pyLDT.py
pyLDT_cosmo/solve_eqns.py
pyLDT_cosmo/sph_coll_eqns.py
pyLDT_cosmo/benchmarks/pdf_gr_z0.0_R10.dat
pyLDT_cosmo/benchmarks/pdf_gr_z0.5_R10.dat
pyLDT_cosmo/benchmarks/pdf_gr_z1.0_R10.dat
pyLDT_cosmo/benchmarks/pdf_lcdm_z0.0_R10.dat
pyLDT_cosmo/benchmarks/pdf_lcdm_z0.5_R10.dat
pyLDT_cosmo/benchmarks/pdf_lcdm_z1.0_R10.dat
pyLDT_cosmo/benchmarks/rho.dat
pyLDT_cosmo/tests/__init__.py
pyLDT_cosmo/tests/test_pyLDT.py
pyLDT_cosmo-1.0.4.dist-info/LICENSE
pyLDT_cosmo-1.0.4.dist-info/METADATA
pyLDT_cosmo-1.0.4.dist-info/WHEEL
pyLDT_cosmo-1.0.4.dist-info/top_level.txt
pyLDT_cosmo-1.0.4.dist-info/RECORD
