Metadata-Version: 2.1
Name: pyLDT-cosmo
Version: 1.0.4
Summary: Package for PDF calculations in Large Deviation Theory
Home-page: https://github.com/mcataneo/pyLDT-cosmo
Author: Matteo Cataneo
Author-email: mcataneo85@gmail.com
License: UNKNOWN
Platform: UNKNOWN
Classifier: Programming Language :: Python :: 3
Classifier: License :: OSI Approved :: MIT License
Classifier: Operating System :: OS Independent
Requires-Python: >=3.7
License-File: LICENSE
Requires-Dist: numpy (==1.19.5)
Requires-Dist: scipy (==1.6.2)
Requires-Dist: camb (==1.3.0)
Requires-Dist: mcfit (==0.0.16)
